infupy/__init__.py
infupy/backends/__init__.py
infupy/backends/alaris.py
infupy/backends/common.py
infupy/backends/fresenius.py
infupy/gui/__init__.py
infupy/gui/syringorecueil_ui.py
infupy-0.5.data/scripts/syre.pyw
infupy-0.5.dist-info/DESCRIPTION.rst
infupy-0.5.dist-info/METADATA
infupy-0.5.dist-info/RECORD
infupy-0.5.dist-info/WHEEL
infupy-0.5.dist-info/metadata.json
infupy-0.5.dist-info/top_level.txt
